{"collection":"netzwerk-a1-kursbuch","items":[
{"page":163,"activity_type":"vocabulary","topic":"none","summary":"Alphabetical word list appendix, letters A to B (Anweisung–Bett)."},
{"page":164,"activity_type":"vocabulary","topic":"none","summary":"Alphabetical word list appendix, letters B to E (bewegen–Ehefrau)."},
{"page":165,"activity_type":"vocabulary","topic":"none","summary":"Alphabetical word list appendix, letters E to F (Ehemann–frei)."},
{"page":166,"activity_type":"vocabulary","topic":"none","summary":"Alphabetical word list appendix, letters F to H (frei–Hand)."},
{"page":167,"activity_type":"vocabulary","topic":"none","summary":"Alphabetical word list appendix, letters H to K (Händler–Keks)."},
{"page":168,"activity_type":"vocabulary","topic":"none","summary":"Alphabetical word list appendix, letters K to M (Kellner–Mann)."},
{"page":169,"activity_type":"vocabulary","topic":"none","summary":"Alphabetical word list appendix, letters M to N (Mann–November)."},
{"page":170,"activity_type":"vocabulary","topic":"none","summary":"Alphabetical word list appendix, letters N to R (Nudel–reisen)."},
{"page":171,"activity_type":"vocabulary","topic":"none","summary":"Alphabetical word list appendix, letters R to S (Reisetasche–Ski-Urlaub)."},
{"page":172,"activity_type":"vocabulary","topic":"none","summary":"Alphabetical word list appendix, letters S to T (Small Talk–Toilette)."},
{"page":173,"activity_type":"vocabulary","topic":"none","summary":"Alphabetical word list appendix, letters T to V (toll–Vorschlag)."},
{"page":174,"activity_type":"vocabulary","topic":"none","summary":"Alphabetical word list appendix, letters V to Z (vorspielen–zwölf)."}
]}
